[
    {
        "path": "20220731-homily",
        "type": "directory",
        "md5": false
    },
    {
        "path": "/20220731-homily/index.html",
        "type": "file",
        "md5": "e4183a4c11b8243545cac6ff9b589395"
    },
    {
        "path": "20220807-homily",
        "type": "directory",
        "md5": false
    },
    {
        "path": "/20220807-homily/index.html",
        "type": "file",
        "md5": "ff33670670067fcd66fb6c32a1a4b17b"
    },
    {
        "path": "20220814-homily",
        "type": "directory",
        "md5": false
    },
    {
        "path": "/20220814-homily/index.html",
        "type": "file",
        "md5": "88be5de3ce31914485bc4528ffa5d235"
    },
    {
        "path": "20220821-homily",
        "type": "directory",
        "md5": false
    },
    {
        "path": "/20220821-homily/index.html",
        "type": "file",
        "md5": "32c30ea211254234152657c18e7f15c3"
    },
    {
        "path": "404.html",
        "type": "file",
        "md5": "aeb07a1f2b0d2a77c72aad0f472963bf"
    },
    {
        "path": "assets",
        "type": "directory",
        "md5": false
    },
    {
        "path": "assets/css",
        "type": "directory",
        "md5": false
    },
    {
        "path": "/assets/css/editor.css",
        "type": "file",
        "md5": "4202808df745f2ac7ab250606fa0d272"
    },
    {
        "path": "/assets/css/main.css",
        "type": "file",
        "md5": "cb9f0c010889a7919feb96d5e6b3b993"
    },
    {
        "path": "/assets/css/photoswipe.css",
        "type": "file",
        "md5": "7331f6eb15671b2fc8e3ffd46e849f7b"
    },
    {
        "path": "/assets/css/style.css",
        "type": "file",
        "md5": "33428cfadd3120020e916bc35092efd7"
    },
    {
        "path": "assets/dynamic",
        "type": "directory",
        "md5": false
    },
    {
        "path": "assets/js",
        "type": "directory",
        "md5": false
    },
    {
        "path": "/assets/js/photoswipe-ui-default.min.js",
        "type": "file",
        "md5": "9952f77ca2b8fbc9449a268008ea8dee"
    },
    {
        "path": "/assets/js/photoswipe.min.js",
        "type": "file",
        "md5": "b586a3bc288c989ecce7b81b48e35855"
    },
    {
        "path": "/assets/js/scripts.js",
        "type": "file",
        "md5": "e0c4d53c21e83015f166f4b853f8ade4"
    },
    {
        "path": "/assets/js/scripts.min.js",
        "type": "file",
        "md5": "f47c11534595205f20935f0db2a62a85"
    },
    {
        "path": "/assets/js/svg-fix.js",
        "type": "file",
        "md5": "9b7d020c55e2b4f77ab40c97f88f9ff4"
    },
    {
        "path": "/assets/js/svg-map.js",
        "type": "file",
        "md5": "3f007dc85fd8629e11dad3e000154b2b"
    },
    {
        "path": "assets/svg",
        "type": "directory",
        "md5": false
    },
    {
        "path": "/assets/svg/gallery-icons-dark.svg",
        "type": "file",
        "md5": "a4f588d02a5173243813af82b5d5546e"
    },
    {
        "path": "/assets/svg/gallery-icons-light.svg",
        "type": "file",
        "md5": "38f529a5cfc8469010687b31596e8208"
    },
    {
        "path": "/assets/svg/svg-map.svg",
        "type": "file",
        "md5": "25970b4dc9b91773247e995cb3d0318a"
    },
    {
        "path": "authors",
        "type": "directory",
        "md5": false
    },
    {
        "path": "authors/fr-david-baunach",
        "type": "directory",
        "md5": false
    },
    {
        "path": "/authors/fr-david-baunach/index.html",
        "type": "file",
        "md5": "4b024c67a094eca9ad252fd3676939af"
    },
    {
        "path": "authors/fr-david-baunach/page",
        "type": "directory",
        "md5": false
    },
    {
        "path": "authors/fr-david-baunach/page/2",
        "type": "directory",
        "md5": false
    },
    {
        "path": "/authors/fr-david-baunach/page/2/index.html",
        "type": "file",
        "md5": "7b6566bb7a0d06ad4f727ed2508d816e"
    },
    {
        "path": "feed.json",
        "type": "file",
        "md5": "e5073f186d8cd9f43824f0183be273d9"
    },
    {
        "path": "feed.xml",
        "type": "file",
        "md5": "403bacb09dac4d4e4ccf694221242b4b"
    },
    {
        "path": "hello-world",
        "type": "directory",
        "md5": false
    },
    {
        "path": "/hello-world/index.html",
        "type": "file",
        "md5": "7b222b9f981f2bc9b6abad04d3ac6d2c"
    },
    {
        "path": "index.html",
        "type": "file",
        "md5": "b9206614c3848a38fa496c0376d7a2cf"
    },
    {
        "path": "media",
        "type": "directory",
        "md5": false
    },
    {
        "path": "media/posts",
        "type": "directory",
        "md5": false
    },
    {
        "path": "media/posts/5",
        "type": "directory",
        "md5": false
    },
    {
        "path": "/media/posts/5/640px-Paolo_Veronese_-_The_Marriage_at_Cana_detail_-_WGA24859.jpg",
        "type": "file",
        "md5": "1744dcf8df7df45082795d35f21cc1fe"
    },
    {
        "path": "media/posts/5/responsive",
        "type": "directory",
        "md5": false
    },
    {
        "path": "/media/posts/5/responsive/640px-Paolo_Veronese_-_The_Marriage_at_Cana_detail_-_WGA24859-2xl.jpg",
        "type": "file",
        "md5": "db57b278926eed8f359496bd33a339d1"
    },
    {
        "path": "/media/posts/5/responsive/640px-Paolo_Veronese_-_The_Marriage_at_Cana_detail_-_WGA24859-lg.jpg",
        "type": "file",
        "md5": "db57b278926eed8f359496bd33a339d1"
    },
    {
        "path": "/media/posts/5/responsive/640px-Paolo_Veronese_-_The_Marriage_at_Cana_detail_-_WGA24859-md.jpg",
        "type": "file",
        "md5": "db57b278926eed8f359496bd33a339d1"
    },
    {
        "path": "/media/posts/5/responsive/640px-Paolo_Veronese_-_The_Marriage_at_Cana_detail_-_WGA24859-sm.jpg",
        "type": "file",
        "md5": "9805a57c08d7f77b5a3464396d1d3a00"
    },
    {
        "path": "/media/posts/5/responsive/640px-Paolo_Veronese_-_The_Marriage_at_Cana_detail_-_WGA24859-xl.jpg",
        "type": "file",
        "md5": "db57b278926eed8f359496bd33a339d1"
    },
    {
        "path": "/media/posts/5/responsive/640px-Paolo_Veronese_-_The_Marriage_at_Cana_detail_-_WGA24859-xs.jpg",
        "type": "file",
        "md5": "cb174ea00878105f1119ace417c5b8bc"
    },
    {
        "path": "media/posts/6",
        "type": "directory",
        "md5": false
    },
    {
        "path": "/media/posts/6/1024px-Rembrandt_van_Rijn_Christ_Preaching_La_petite_Tombe_c._1652_NGA_43413.jpg",
        "type": "file",
        "md5": "5de7d7987da3f9469e3b7c41dc11fc9a"
    },
    {
        "path": "media/posts/6/responsive",
        "type": "directory",
        "md5": false
    },
    {
        "path": "/media/posts/6/responsive/1024px-Rembrandt_van_Rijn_Christ_Preaching_La_petite_Tombe_c._1652_NGA_43413-2xl.jpg",
        "type": "file",
        "md5": "62a4cbd03c9cdd72e4ecdca66f5312ec"
    },
    {
        "path": "/media/posts/6/responsive/1024px-Rembrandt_van_Rijn_Christ_Preaching_La_petite_Tombe_c._1652_NGA_43413-lg.jpg",
        "type": "file",
        "md5": "62a4cbd03c9cdd72e4ecdca66f5312ec"
    },
    {
        "path": "/media/posts/6/responsive/1024px-Rembrandt_van_Rijn_Christ_Preaching_La_petite_Tombe_c._1652_NGA_43413-md.jpg",
        "type": "file",
        "md5": "cfce11b767d0c9af3d0d7ecb341cf10c"
    },
    {
        "path": "/media/posts/6/responsive/1024px-Rembrandt_van_Rijn_Christ_Preaching_La_petite_Tombe_c._1652_NGA_43413-sm.jpg",
        "type": "file",
        "md5": "f5671d68006f6ba617f9b8ad5cc2af24"
    },
    {
        "path": "/media/posts/6/responsive/1024px-Rembrandt_van_Rijn_Christ_Preaching_La_petite_Tombe_c._1652_NGA_43413-xl.jpg",
        "type": "file",
        "md5": "62a4cbd03c9cdd72e4ecdca66f5312ec"
    },
    {
        "path": "/media/posts/6/responsive/1024px-Rembrandt_van_Rijn_Christ_Preaching_La_petite_Tombe_c._1652_NGA_43413-xs.jpg",
        "type": "file",
        "md5": "fabc99214d0b2e83030074a9cf0fa6e0"
    },
    {
        "path": "media/posts/7",
        "type": "directory",
        "md5": false
    },
    {
        "path": "/media/posts/7/797px-Harrowing_of_hell_Christ_leads_Adam_by_the_hand._On_scroll_in_border_the_motto_Entre_tenir_Dieu_le_viuelle_f._125_Cropped.jpg",
        "type": "file",
        "md5": "f5cb42b46f26058b0b7f55c3d38fae92"
    },
    {
        "path": "media/posts/7/responsive",
        "type": "directory",
        "md5": false
    },
    {
        "path": "/media/posts/7/responsive/797px-Harrowing_of_hell_Christ_leads_Adam_by_the_hand._On_scroll_in_border_the_motto_Entre_tenir_Dieu_le_viuelle_f._125_Cropped-2xl.jpg",
        "type": "file",
        "md5": "d1c85a75b28c369ba7b00a93228edbfd"
    },
    {
        "path": "/media/posts/7/responsive/797px-Harrowing_of_hell_Christ_leads_Adam_by_the_hand._On_scroll_in_border_the_motto_Entre_tenir_Dieu_le_viuelle_f._125_Cropped-lg.jpg",
        "type": "file",
        "md5": "d1c85a75b28c369ba7b00a93228edbfd"
    },
    {
        "path": "/media/posts/7/responsive/797px-Harrowing_of_hell_Christ_leads_Adam_by_the_hand._On_scroll_in_border_the_motto_Entre_tenir_Dieu_le_viuelle_f._125_Cropped-md.jpg",
        "type": "file",
        "md5": "a934b18bb35add2dbc0abb2e91dabaab"
    },
    {
        "path": "/media/posts/7/responsive/797px-Harrowing_of_hell_Christ_leads_Adam_by_the_hand._On_scroll_in_border_the_motto_Entre_tenir_Dieu_le_viuelle_f._125_Cropped-sm.jpg",
        "type": "file",
        "md5": "1039a2611a295f374d9cfcefc4aa7d1d"
    },
    {
        "path": "/media/posts/7/responsive/797px-Harrowing_of_hell_Christ_leads_Adam_by_the_hand._On_scroll_in_border_the_motto_Entre_tenir_Dieu_le_viuelle_f._125_Cropped-xl.jpg",
        "type": "file",
        "md5": "d1c85a75b28c369ba7b00a93228edbfd"
    },
    {
        "path": "/media/posts/7/responsive/797px-Harrowing_of_hell_Christ_leads_Adam_by_the_hand._On_scroll_in_border_the_motto_Entre_tenir_Dieu_le_viuelle_f._125_Cropped-xs.jpg",
        "type": "file",
        "md5": "afebcea0b630232b7768d53a9efd788c"
    },
    {
        "path": "media/posts/8",
        "type": "directory",
        "md5": false
    },
    {
        "path": "media/posts/8/responsive",
        "type": "directory",
        "md5": false
    },
    {
        "path": "/media/posts/8/responsive/the-holy-family-f7355c-2xl.jpg",
        "type": "file",
        "md5": "be279f46b9ade56e50e5cb9346c6a9f0"
    },
    {
        "path": "/media/posts/8/responsive/the-holy-family-f7355c-lg.jpg",
        "type": "file",
        "md5": "be279f46b9ade56e50e5cb9346c6a9f0"
    },
    {
        "path": "/media/posts/8/responsive/the-holy-family-f7355c-md.jpg",
        "type": "file",
        "md5": "294b41ffb61fb53afe5d50f4aaf24225"
    },
    {
        "path": "/media/posts/8/responsive/the-holy-family-f7355c-sm.jpg",
        "type": "file",
        "md5": "9136fa7b055754ab2a988a2784d78205"
    },
    {
        "path": "/media/posts/8/responsive/the-holy-family-f7355c-xl.jpg",
        "type": "file",
        "md5": "be279f46b9ade56e50e5cb9346c6a9f0"
    },
    {
        "path": "/media/posts/8/responsive/the-holy-family-f7355c-xs.jpg",
        "type": "file",
        "md5": "a5b7247b1be24617685b937bbf174493"
    },
    {
        "path": "/media/posts/8/the-holy-family-f7355c.jpg",
        "type": "file",
        "md5": "510f780845d7f26bf593384766adc5da"
    },
    {
        "path": "media/website",
        "type": "directory",
        "md5": false
    },
    {
        "path": "/media/website/DMB00899.jpg",
        "type": "file",
        "md5": "22cbde4a06a212d89bd7e8d3af4c30a8"
    },
    {
        "path": "media/website/responsive",
        "type": "directory",
        "md5": false
    },
    {
        "path": "/media/website/responsive/DMB00899-2xl.jpg",
        "type": "file",
        "md5": "ee92b1a305b21bff7cd9bcb5b5b30ec0"
    },
    {
        "path": "/media/website/responsive/DMB00899-lg.jpg",
        "type": "file",
        "md5": "cd783825def8d71766329863f831a42d"
    },
    {
        "path": "/media/website/responsive/DMB00899-md.jpg",
        "type": "file",
        "md5": "a8d8c476f96af6e851c8e6959bd696dc"
    },
    {
        "path": "/media/website/responsive/DMB00899-sm.jpg",
        "type": "file",
        "md5": "40d6df5f97a3bbf1a7ec146d5ba44d2c"
    },
    {
        "path": "/media/website/responsive/DMB00899-xl.jpg",
        "type": "file",
        "md5": "769fc74e05066cf94f0899345a813dd9"
    },
    {
        "path": "/media/website/responsive/DMB00899-xs.jpg",
        "type": "file",
        "md5": "ce5d1cc7d642da6288aee3bd64bcac25"
    },
    {
        "path": "p2p-messaging",
        "type": "directory",
        "md5": false
    },
    {
        "path": "/p2p-messaging/index.html",
        "type": "file",
        "md5": "eae4c0023ccb7cc82dddfd829c3c2e51"
    },
    {
        "path": "page",
        "type": "directory",
        "md5": false
    },
    {
        "path": "page/2",
        "type": "directory",
        "md5": false
    },
    {
        "path": "/page/2/index.html",
        "type": "file",
        "md5": "2d9059f8b57bb8c43cd3cb473cffc4f2"
    },
    {
        "path": "robots.txt",
        "type": "file",
        "md5": "1d355ed96c525fd5a457a9e682a11bd8"
    },
    {
        "path": "saint-maker-whitepaper",
        "type": "directory",
        "md5": false
    },
    {
        "path": "/saint-maker-whitepaper/index.html",
        "type": "file",
        "md5": "3a16b233d349aa658a54cc857a125539"
    },
    {
        "path": "sitemap.xml",
        "type": "file",
        "md5": "0eee2abe6a2a63f1fbf18c2d6971f8d6"
    },
    {
        "path": "sitemap.xsl",
        "type": "file",
        "md5": "03c2f9a7fdcc46ff05c435907614a0b8"
    },
    {
        "path": "tags",
        "type": "directory",
        "md5": false
    },
    {
        "path": "tags/blog",
        "type": "directory",
        "md5": false
    },
    {
        "path": "/tags/blog/index.html",
        "type": "file",
        "md5": "22a7bdd19cfb8d3542296874ab57e18e"
    },
    {
        "path": "tags/homily",
        "type": "directory",
        "md5": false
    },
    {
        "path": "/tags/homily/index.html",
        "type": "file",
        "md5": "9ff7222a3e8d8e2aeae40833b9bc10d6"
    },
    {
        "path": "/tags/index.html",
        "type": "file",
        "md5": "4d4f4cf7cbca0bc8a4a4b01985d22e90"
    },
    {
        "path": "uber-everything",
        "type": "directory",
        "md5": false
    },
    {
        "path": "/uber-everything/index.html",
        "type": "file",
        "md5": "b0df7d8c2b0f372356075b656820f2be"
    }
]